RenderBirdCore.py
renderbirdcore-0.1.8.1.dist-info/LICENSE
renderbirdcore-0.1.8.1.dist-info/METADATA
renderbirdcore-0.1.8.1.dist-info/WHEEL
renderbirdcore-0.1.8.1.dist-info/top_level.txt
renderbirdcore-0.1.8.1.dist-info/RECORD
