Metadata-Version: 2.2
Name: RenderBirdCore
Version: 0.1.8.1
Summary: A easy to use object-based 3D rendering engine for Python based on PyGame and OpenGL
Home-page: https://github.com/Wojtekb30/RenderBird-Python-3D-engine
Author: Wojtekb30 (Wojciech B)
Author-email: wojtekb30.player@gmail.com
Classifier: Programming Language :: Python :: 3
Classifier: License :: OSI Approved :: MIT License
Classifier: Operating System :: OS Independent
Classifier: Topic :: Software Development :: Libraries
Classifier: Topic :: Multimedia :: Graphics :: 3D Rendering
Requires-Python: >=3.11
License-File: LICENSE
Requires-Dist: pygame>=2.0.0
Requires-Dist: PyOpenGL>=3.1.6
Requires-Dist: Pillow>=8.0.0
Requires-Dist: numpy>=1.18.0
Dynamic: author
Dynamic: author-email
Dynamic: classifier
Dynamic: description
Dynamic: description-content-type
Dynamic: home-page
Dynamic: requires-dist
Dynamic: requires-python
Dynamic: summary
